blazetest/Dockerfile
blazetest/RemoteLogging.Dockerfile
blazetest/__init__.py
blazetest/cli/__init__.py
blazetest/cli/base.py
blazetest/cli/purge.py
blazetest/cli/rerun.py
blazetest/cli/run.py
blazetest/cli/sessions.py
blazetest/cli/utils.py
blazetest/core/__init__.py
blazetest/core/cloud/__init__.py
blazetest/core/cloud/aws/__init__.py
blazetest/core/cloud/aws/aws_lambda.py
blazetest/core/cloud/aws/ecr.py
blazetest/core/cloud/aws/error_handler.py
blazetest/core/cloud/aws/s3_manager.py
blazetest/core/cloud/aws/session.py
blazetest/core/cloud/aws/validators.py
blazetest/core/cloud/aws/workflow.py
blazetest/core/config.py
blazetest/core/container_image/__init__.py
blazetest/core/container_image/base.py
blazetest/core/container_image/tools.py
blazetest/core/infra/__init__.py
blazetest/core/infra/base.py
blazetest/core/infra/tools.py
blazetest/core/license/__init__.py
blazetest/core/license/manager.py
blazetest/core/project_config/__init__.py
blazetest/core/project_config/model.py
blazetest/core/project_config/project_config.py
blazetest/core/project_config/validators.py
blazetest/core/run_test/__init__.py
blazetest/core/run_test/pytest_collect.py
blazetest/core/run_test/result_model.py
blazetest/core/run_test/runner_facade.py
blazetest/core/utils/__init__.py
blazetest/core/utils/allure_utils.py
blazetest/core/utils/aws_console_links.py
blazetest/core/utils/command_executor.py
blazetest/core/utils/exceptions.py
blazetest/core/utils/html_report.py
blazetest/core/utils/logging_config.py
blazetest/core/utils/report_merger.py
blazetest/core/utils/reset.py
blazetest/core/utils/utils.py
blazetest/core/utils/versioning.py
blazetest/scripts/install_browser.sh
blazetest/scripts/install_dependencies.sh
blazetest/selenium_helpers.py
blazetest/tests_runner_handler/__init__.py
blazetest/tests_runner_handler/handler.py
blazetest_beta-2.3.0.dist-info/METADATA
blazetest_beta-2.3.0.dist-info/WHEEL
blazetest_beta-2.3.0.dist-info/entry_points.txt
blazetest_beta-2.3.0.dist-info/RECORD
