Metadata-Version: 2.1
Name: blazetest-beta
Version: 2.3.0
Summary: Blazetest is a CLI tool to run your selenium tests faster and more effectively.
Author: Abrorjon Ruziboev
Author-email: abror.ruzibayev@gmail.com
Requires-Python: >=3.9,<=3.12.4
Classifier: Programming Language :: Python :: 3
Classifier: Programming Language :: Python :: 3.9
Classifier: Programming Language :: Python :: 3.10
Classifier: Programming Language :: Python :: 3.11
Requires-Dist: PyYAML (>=6.0)
Requires-Dist: allure-pytest (>=2.13.2,<3.0.0)
Requires-Dist: allure-python-commons (>=2.13.2,<3.0.0)
Requires-Dist: art (>=6.1,<7.0)
Requires-Dist: boto3 (>=1.26.84)
Requires-Dist: click (>=8.1.3)
Requires-Dist: dacite (>=1.8.0)
Requires-Dist: docker (>=7.0.0,<8.0.0)
Requires-Dist: junitparser (>=3.2.0,<4.0.0)
Requires-Dist: licensing (>=0.39)
Requires-Dist: pyopenssl (>=23.0.0)
Requires-Dist: pytest (>=7.2.2)
Requires-Dist: python-logging-loki (>=0.3.1)
Requires-Dist: toml (>=0.10.2)
Requires-Dist: tqdm (>=4.66.4,<5.0.0)
